{
    "sites": [
        {
            "address": "bundesverfassungsgericht.de",
            "region": ["de"],
            "type": ["case_law"]
        },
        {
            "address": "ris.bka.gv.at",
            "region": ["at"],
            "type": ["legislation"]
        },
        {
            "address": "vwgh.gv.at ",
            "region": ["at"],
            "type": ["case_law"]
        },
        {
            "address": "admin.ch/opc",
            "region": ["ch"],
            "type": ["legislation"]
        }
    ]
}
